filenav/__init__.py
filenav/entrypoint.py
filenav/main.py
filenav/api/__init__.py
filenav/api/file.py
filenav/api/item.py
filenav/api/thumbnail.py
filenav/frontend-dist/index.html
filenav/frontend-dist/assets/favicon-Clnh0Qdz.ico
filenav/frontend-dist/assets/index-B6CZ6QAk.css
filenav/frontend-dist/assets/index-BUApq2n2.js
filenav-0.1.2.dist-info/METADATA
filenav-0.1.2.dist-info/WHEEL
filenav-0.1.2.dist-info/entry_points.txt
filenav-0.1.2.dist-info/RECORD
